models/__init__.py
models/models.py
ai_modules-0.1.0.dist-info/METADATA
ai_modules-0.1.0.dist-info/WHEEL
ai_modules-0.1.0.dist-info/top_level.txt
ai_modules-0.1.0.dist-info/RECORD
