Metadata-Version: 2.1
Name: ai-modules
Version: 0.1.0
Summary: A flexible and extensible framework for managing and processing various types of data objects using AI techniques.
Home-page: https://github.com/Cdaprod/AI-Modules
Author: Your Name
Author-email: your.email@example.com
Classifier: Development Status :: 3 - Alpha
Classifier: Intended Audience :: Developers
Classifier: License :: OSI Approved :: MIT License
Classifier: Operating System :: OS Independent
Classifier: Programming Language :: Python :: 3
Classifier: Programming Language :: Python :: 3.9
Classifier: Programming Language :: Python :: 3.10
Classifier: Programming Language :: Python :: 3.11
Classifier: Programming Language :: Python :: 3.12
Requires-Python: >=3.9
Requires-Dist: fastapi <0.69.0,>=0.68.0
Requires-Dist: pydantic <2.0.0,>=1.8.0
Requires-Dist: uvicorn <0.16.0,>=0.15.0
Provides-Extra: dev
Requires-Dist: pytest <7.0.0,>=6.2.4 ; extra == 'dev'
Requires-Dist: pytest-cov <3.0.0,>=2.12.0 ; extra == 'dev'
Requires-Dist: flake8 <4.0.0,>=3.9.2 ; extra == 'dev'
Requires-Dist: black <22.0,>=21.5b1 ; extra == 'dev'
